pfmsoft/__init__.py
pfmsoft/aiohttp_queue/__init__.py
pfmsoft/aiohttp_queue/aiohttp.py
pfmsoft/aiohttp_queue/callbacks.py
pfmsoft/aiohttp_queue/runners.py
pfmsoft/aiohttp_queue/utilities.py
Pfmsoft_Aiohttp_Queue-0.2.1.dist-info/AUTHORS.rst
Pfmsoft_Aiohttp_Queue-0.2.1.dist-info/LICENSE
Pfmsoft_Aiohttp_Queue-0.2.1.dist-info/METADATA
Pfmsoft_Aiohttp_Queue-0.2.1.dist-info/WHEEL
Pfmsoft_Aiohttp_Queue-0.2.1.dist-info/top_level.txt
Pfmsoft_Aiohttp_Queue-0.2.1.dist-info/RECORD
