Metadata-Version: 2.1
Name: Pfmsoft-Aiohttp-Queue
Version: 0.2.1
Summary: A library to support aiohttp requests in a Queue, with callbacks for success, failure, or retry.
Home-page: https://github.com/DonalChilde/pfmsoft_aiohttp_queue
Author: UNKNOWN
Author-email: UNKNOWN
License: MIT license
Keywords: Python pfmsoft_aiohttp_queue
Platform: UNKNOWN
Classifier: Development Status :: 2 - Pre-Alpha
Classifier: Intended Audience :: Developers
Classifier: Natural Language :: English
Classifier: License :: OSI Approved :: MIT License
Classifier: Programming Language :: Python :: 3
Classifier: Programming Language :: Python :: 3.8
